{"stats":{"minecraft:used":{"minecraft:wandering_trader_spawn_egg":8,"minecraft:magma_cube_spawn_egg":7,"minecraft:piglin_spawn_egg":39,"mixcraft:diamondiron_sword":30},"minecraft:custom":{"minecraft:jump":32,"minecraft:time_since_rest":4279,"minecraft:damage_dealt":2280,"minecraft:leave_game":1,"minecraft:sprint_one_cm":1340,"minecraft:play_time":4279,"minecraft:time_since_death":4279,"minecraft:walk_one_cm":13600,"minecraft:sneak_time":10,"minecraft:total_world_time":4330,"minecraft:talked_to_villager":1,"minecraft:drop":2,"minecraft:fly_one_cm":40535},"minecraft:dropped":{"minecraft:mutton":1,"minecraft:white_wool":1},"minecraft:picked_up":{"minecraft:rotten_flesh":1,"minecraft:mutton":1,"minecraft:white_wool":3,"minecraft:egg":1}},"DataVersion":3465}